pai_llm/__init__.py
pai_llm/adapter/__init__.py
pai_llm/adapter/langchain_openai/__init__.py
pai_llm/conversation/__init__.py
pai_llm/conversation/algorithm/__init__.py
pai_llm/conversation/algorithm/base.py
pai_llm/conversation/algorithm/fifo.py
pai_llm/conversation/exceptions.py
pai_llm/conversation/history.py
pai_llm/conversation/integration/__init__.py
pai_llm/conversation/integration/langchain.py
pai_llm/conversation/integration/openai.py
pai_llm/conversation/models.py
pai_llm/conversation/storage/__init__.py
pai_llm/conversation/storage/base.py
pai_llm/conversation/storage/memory_storage.py
pai_llm/conversation/storage/mysql_storage.py
pai_llm/conversation/storage/redis_storage.py
pai_llm/conversation/storage/sql_storage.py
pai_llm/conversation/storage/sqlite_storage.py
pai_llm/dspy/__init__.py
pai_llm/exceptions.py
pai_llm/prompt/__init__.py
pai_llm/types/__init__.py
pai_llm/types/chat/__init__.py
pai_llm/types/chat/completion_role.py
pai_llm/types/media/__init__.py
pai_llm/types/media/base.py
pai_llm/types/media/document.py
pai_llm/types/model/__init__.py
pai_llm/types/model/model.py
pai_llm/types/model/unified_model.py
pai_llm-0.2.4.dist-info/METADATA
pai_llm-0.2.4.dist-info/WHEEL
pai_llm-0.2.4.dist-info/RECORD
